{
  "version": "owm_wind_grid_v1",
  "ts": "2026-03-03T11:03:00Z",
  "bounds": {
    "south": -51.618017,
    "north": -29.382175,
    "west": 158.291016,
    "east": -172.353516
  },
  "grid": {
    "rows": 3,
    "cols": 3
  },
  "points": [
    {
      "lat": -51.618017,
      "lon": 158.291016,
      "speed": 6.45,
      "degFrom": 313,
      "degTo": 133,
      "u": 4.71723137544365,
      "v": -4.398889422403115,
      "gust": 8.94
    },
    {
      "lat": -51.618017,
      "lon": 172.96875,
      "speed": 6.6,
      "degFrom": 306,
      "degTo": 126,
      "u": 5.3395121628746525,
      "v": -3.8793826651303216,
      "gust": 8.92
    },
    {
      "lat": -51.618017,
      "lon": -172.353516,
      "speed": 7.29,
      "degFrom": 173,
      "degTo": 353,
      "u": -0.8884275134235298,
      "v": 7.2356614454652375,
      "gust": 7.79
    },
    {
      "lat": -40.500096,
      "lon": 158.291016,
      "speed": 8.33,
      "degFrom": 6,
      "degTo": 186,
      "u": -0.87072209901955,
      "v": -8.284367388417717,
      "gust": 9.99
    },
    {
      "lat": -40.500096,
      "lon": 172.96875,
      "speed": 2.58,
      "degFrom": 34,
      "degTo": 214,
      "u": -1.4427176909545265,
      "v": -2.138916937192008,
      "gust": 3.22
    },
    {
      "lat": -40.500096,
      "lon": -172.353516,
      "speed": 16.7,
      "degFrom": 276,
      "degTo": 96,
      "u": 16.608515652650166,
      "v": -1.7456253365698107,
      "gust": 18.76
    },
    {
      "lat": -29.382175,
      "lon": 158.291016,
      "speed": 8.47,
      "degFrom": 81,
      "degTo": 261,
      "u": -8.365720244840817,
      "v": -1.324999918890757,
      "gust": 8.55
    },
    {
      "lat": -29.382175,
      "lon": 172.96875,
      "speed": 9.28,
      "degFrom": 125,
      "degTo": 305,
      "u": -7.601730971001843,
      "v": 5.322789329337707,
      "gust": 9.23
    },
    {
      "lat": -29.382175,
      "lon": -172.353516,
      "speed": 5.94,
      "degFrom": 245,
      "degTo": 65,
      "u": 5.383468254997701,
      "v": 2.5103524747397548,
      "gust": 5.97
    }
  ],
  "okCount": 9,
  "failCount": 0
}