{
  "version": "owm_wind_grid_v1",
  "ts": "2026-03-01T12:03:00Z",
  "bounds": {
    "south": -51.618017,
    "north": -29.382175,
    "west": 158.291016,
    "east": -172.353516
  },
  "grid": {
    "rows": 3,
    "cols": 3
  },
  "points": [
    {
      "lat": -51.618017,
      "lon": 158.291016,
      "speed": 1.82,
      "degFrom": 22,
      "degTo": 202,
      "u": -0.6817840000169599,
      "v": -1.6874746153115532,
      "gust": 2.1
    },
    {
      "lat": -51.618017,
      "lon": 172.96875,
      "speed": 12.61,
      "degFrom": 193,
      "degTo": 13,
      "u": 2.8366327952761377,
      "v": 12.286806516941816,
      "gust": 14.13
    },
    {
      "lat": -51.618017,
      "lon": -172.353516,
      "speed": 11.34,
      "degFrom": 300,
      "degTo": 120,
      "u": 9.820728078915534,
      "v": -5.669999999999997,
      "gust": 12.63
    },
    {
      "lat": -40.500096,
      "lon": 158.291016,
      "speed": 4.13,
      "degFrom": 115,
      "degTo": 295,
      "u": -3.7430511604613637,
      "v": 1.7454134209890892,
      "gust": 4.13
    },
    {
      "lat": -40.500096,
      "lon": 172.96875,
      "speed": 16.1,
      "degFrom": 116,
      "degTo": 296,
      "u": -14.470584145416591,
      "v": 7.0577754633041465,
      "gust": 15.54
    },
    {
      "lat": -40.500096,
      "lon": -172.353516,
      "speed": 5.13,
      "degFrom": 24,
      "degTo": 204,
      "u": -2.0865589789788532,
      "v": -4.686488197706543,
      "gust": 6.2
    },
    {
      "lat": -29.382175,
      "lon": 158.291016,
      "speed": 8.97,
      "degFrom": 119,
      "degTo": 299,
      "u": -7.845338773040384,
      "v": 4.3487422936096385,
      "gust": 9.62
    },
    {
      "lat": -29.382175,
      "lon": 172.96875,
      "speed": 7.18,
      "degFrom": 150,
      "degTo": 330,
      "u": -3.590000000000003,
      "v": 6.218062399172267,
      "gust": 7.36
    },
    {
      "lat": -29.382175,
      "lon": -172.353516,
      "speed": 13.59,
      "degFrom": 331,
      "degTo": 151,
      "u": 6.588562739147722,
      "v": -11.886081820024389,
      "gust": 21.11
    }
  ],
  "okCount": 9,
  "failCount": 0
}